AlienUpgrade/__init__.py
AlienUpgrade/ultimate.py
AlienUpgrade-0.0.2.dist-info/METADATA
AlienUpgrade-0.0.2.dist-info/WHEEL
AlienUpgrade-0.0.2.dist-info/top_level.txt
AlienUpgrade-0.0.2.dist-info/RECORD
