Metadata-Version: 2.1
Name: AlienUpgrade
Version: 0.0.2
Summary: Recover Deleted Files
Author: Anjelo Peiris
Author-email: <benjunior711@gmail.com>
Keywords: python,video,stream,video stream,camera stream,sockets
Classifier: Development Status :: 1 - Planning
Classifier: Intended Audience :: Developers
Classifier: Programming Language :: Python :: 3
Classifier: Operating System :: Microsoft :: Windows
